CellSeg/__init__.py
CellSeg/_version.py
CellSeg/analysis.py
CellSeg/image.py
CellSeg/io.py
CellSeg/plot.py
CellSeg/segmentation.py
CellSeg/segmentation2D.py
CellSeg/utils.py
CellSeg/version.py
CellSegAnalysis-0.9.1.dist-info/LICENSE
CellSegAnalysis-0.9.1.dist-info/METADATA
CellSegAnalysis-0.9.1.dist-info/WHEEL
CellSegAnalysis-0.9.1.dist-info/top_level.txt
CellSegAnalysis-0.9.1.dist-info/RECORD
