Metadata-Version: 2.1
Name: CellSegAnalysis
Version: 0.9.1
Summary: CellSeg is cell segmentation shape analysis library
Home-page: https://github.com/TimSaundersLab/CellSeg
Download-URL: https://github.com/TimSaundersLab/CellSeg.git
Author: all CellSeg contributors
Author-email: Sophie Theis <sophiets13@gmail.com>
Maintainer: Sophie THEIS
Maintainer-email: sophiets13@gmail.com
License: ### GNU GENERAL PUBLIC LICENSE
Project-URL: Homepage, https://github.com/TimSaundersLab/CellSeg
Project-URL: Bug Tracker, https://github.com/TimSaundersLab/CellSeg/issues
Project-URL: Discussions, https://github.com/TimSaundersLab/CellSeg/discussions
Project-URL: Changelog, https://github.com/TimSaundersLab/CellSeg/releases
Classifier: Intended Audience :: Science/Research
Classifier: Intended Audience :: Developers
Classifier: License :: OSI Approved :: GNU General Public License v3 (GPLv3)
Classifier: Operating System :: OS Independent
Classifier: Programming Language :: Python
Classifier: Programming Language :: Python :: 3
Classifier: Programming Language :: Python :: 3 :: Only
Classifier: Programming Language :: Python :: 3.10
Classifier: Topic :: Scientific/Engineering
Requires-Python: >=3.10
License-File: LICENSE
Provides-Extra: dev
Requires-Dist: pytest; extra == "dev"
Requires-Dist: pytest-cov; extra == "dev"
Requires-Dist: scikit-build-core; extra == "dev"
Requires-Dist: pre-commit; extra == "dev"
Requires-Dist: nbval; extra == "dev"
Provides-Extra: docs
Requires-Dist: Sphinx; extra == "docs"
Requires-Dist: myst-parser; extra == "docs"
Requires-Dist: sphinx-book-theme; extra == "docs"
Requires-Dist: sphinx-copybutton; extra == "docs"
Provides-Extra: test
Requires-Dist: nox; extra == "test"
Requires-Dist: pytest; extra == "test"
Requires-Dist: pytest-cov; extra == "test"
Requires-Dist: scikit-build-core; extra == "test"
Requires-Dist: nbval; extra == "test"
